pyreusion/__init__.py
pyreusion/pyreusion.py
pyreusion-1.1.1.0.dist-info/LICENSE
pyreusion-1.1.1.0.dist-info/METADATA
pyreusion-1.1.1.0.dist-info/WHEEL
pyreusion-1.1.1.0.dist-info/top_level.txt
pyreusion-1.1.1.0.dist-info/RECORD
