Metadata-Version: 2.1
Name: pyreusion
Version: 1.1.1.0
Summary: Common method integration in the process of Python programming.
Home-page: https://github.com/Arludesi/pyreusion.git
Author: JoeYoung
Author-email: 1022104172@qq.com
Classifier: License :: OSI Approved :: GNU General Public License v3 (GPLv3)
Requires-Python: >=3.6
License-File: LICENSE
